codecraft_tic_tac_toe/__init__.py
codecraft_tic_tac_toe/mock_game.py
codecraft_tic_tac_toe/mock_game_tests.py
codecraft_tic_tac_toe-0.1.5.dist-info/METADATA
codecraft_tic_tac_toe-0.1.5.dist-info/WHEEL
codecraft_tic_tac_toe-0.1.5.dist-info/top_level.txt
codecraft_tic_tac_toe-0.1.5.dist-info/RECORD
