Metadata-Version: 2.1
Name: codecraft-tic-tac-toe
Version: 0.1.5
Summary: This package will allow you to get familiar with the API used in the Codecraft Works Python Tic-Tac-Toe Game
Author: Codecraft Works
Author-email: hello@codecraftworks.com
License: UNKNOWN
Platform: UNKNOWN
Requires-Python: <4.0,>=3.8
Requires-Dist: numpy (==1.22.0)
